ultimate_hosts_blacklist/comparison/__init__.py
ultimate_hosts_blacklist/comparison/configuration.py
ultimate_hosts_blacklist/comparison/core.py
ultimate_hosts_blacklist_comparison-1.2.0.dist-info/LICENSE
ultimate_hosts_blacklist_comparison-1.2.0.dist-info/METADATA
ultimate_hosts_blacklist_comparison-1.2.0.dist-info/WHEEL
ultimate_hosts_blacklist_comparison-1.2.0.dist-info/entry_points.txt
ultimate_hosts_blacklist_comparison-1.2.0.dist-info/top_level.txt
ultimate_hosts_blacklist_comparison-1.2.0.dist-info/RECORD
