Metadata-Version: 2.1
Name: ultimate-hosts-blacklist-comparison
Version: 1.2.0
Summary: The comparison tool of the Ultimate Hosts Blacklist project.
Home-page: https://github.com/Ultimate-Hosts-Blacklist/dev-center/tree/comparison
Author: UNKNOWN
Author-email: UNKNOWN
License: MIT
Keywords: Python,hosts,hosts file
Platform: any
Classifier: Environment :: Console
Classifier: Topic :: Internet
Classifier: Development Status :: 5 - Production/Stable
Classifier: Intended Audience :: Developers
Classifier: Programming Language :: Python
Classifier: Programming Language :: Python :: 3
Classifier: License :: OSI Approved :: MIT License
Requires-Dist: colorama
Requires-Dist: PyFunceble-dev
Requires-Dist: ultimate-hosts-blacklist-helpers
Requires-Dist: ultimate-hosts-blacklist-whitelist
